Metadata-Version: 1.1
Name: decu
Version: 0.0.1
Summary: Decu is a Experimental Computation Utility
Home-page: https://github.com/leotrs/decu
Author: Leo Torres
Author-email: leo@leotrs.com
License: MIT
Download-URL: https://github.com/leotrs/decdu/archive/0.0.1.tar.gz
Platform: any
